{
  "root": "/mnt/e/01_General_Files/Lukas/Final Products",
  "processed_files": 8,
  "items": [
    {
      "file": "/mnt/e/01_General_Files/Lukas/Final Products/ALLEN DEFENDANT'S MOTION TO SUPPRESS EVIDENCE AND STATEMENTS OBTAINED AS A RESULT OF UNLAWFUL ARREST.docx",
      "process_ok": false,
      "text_len": 0,
      "entities_count": 0,
      "legal_ok": true,
      "legal_issues": 0,
      "compliance_checks": 2,
      "irac_ok": false,
      "toulmin_ok": false,
      "citations_found": 0,
      "precedents_ok": false,
      "violations_count": 0
    },
    {
      "file": "/mnt/e/01_General_Files/Lukas/Final Products/Allen_Lukas_Motion_To_Dismiss_Surpress.docx",
      "process_ok": false,
      "text_len": 0,
      "entities_count": 0,
      "legal_ok": true,
      "legal_issues": 0,
      "compliance_checks": 2,
      "irac_ok": false,
      "toulmin_ok": false,
      "citations_found": 0,
      "precedents_ok": false,
      "violations_count": 0
    },
    {
      "file": "/mnt/e/01_General_Files/Lukas/Final Products/DEFENDANT'S MOTION TO SUPPRESS EVIDENCE AND STATEMENTS OBTAINED AS A RESULT OF UNLAWFUL ARREST.docx",
      "process_ok": false,
      "text_len": 0,
      "entities_count": 0,
      "legal_ok": true,
      "legal_issues": 0,
      "compliance_checks": 2,
      "irac_ok": false,
      "toulmin_ok": false,
      "citations_found": 0,
      "precedents_ok": false,
      "violations_count": 0
    },
    {
      "file": "/mnt/e/01_General_Files/Lukas/Final Products/Exhibit 1.docx",
      "process_ok": false,
      "text_len": 0,
      "entities_count": 0,
      "legal_ok": true,
      "legal_issues": 0,
      "compliance_checks": 2,
      "irac_ok": false,
      "toulmin_ok": false,
      "citations_found": 0,
      "precedents_ok": false,
      "violations_count": 0
    },
    {
      "file": "/mnt/e/01_General_Files/Lukas/Final Products/Exhibit 2.docx",
      "process_ok": false,
      "text_len": 0,
      "entities_count": 0,
      "legal_ok": true,
      "legal_issues": 0,
      "compliance_checks": 2,
      "irac_ok": false,
      "toulmin_ok": false,
      "citations_found": 0,
      "precedents_ok": false,
      "violations_count": 0
    },
    {
      "file": "/mnt/e/01_General_Files/Lukas/Final Products/Exhibit_E_ProPublica_Investigation.docx",
      "process_ok": false,
      "text_len": 0,
      "entities_count": 0,
      "legal_ok": true,
      "legal_issues": 0,
      "compliance_checks": 2,
      "irac_ok": false,
      "toulmin_ok": false,
      "citations_found": 0,
      "precedents_ok": false,
      "violations_count": 0
    },
    {
      "file": "/mnt/e/01_General_Files/Lukas/Final Products/KY_Juvenile_Deferral_Analysis_Breckinridge_Deviations_Lukas_Allen_Court_20250602.docx",
      "process_ok": false,
      "text_len": 0,
      "entities_count": 0,
      "legal_ok": true,
      "legal_issues": 0,
      "compliance_checks": 2,
      "irac_ok": false,
      "toulmin_ok": false,
      "citations_found": 0,
      "precedents_ok": false,
      "violations_count": 0
    },
    {
      "file": "/mnt/e/01_General_Files/Lukas/Final Products/Lab Report Assessment.pdf",
      "process_ok": false,
      "text_len": 0,
      "entities_count": 0,
      "legal_ok": true,
      "legal_issues": 0,
      "compliance_checks": 2,
      "irac_ok": false,
      "toulmin_ok": false,
      "citations_found": 0,
      "precedents_ok": false,
      "violations_count": 0
    }
  ]
}